{
    "swagger": "3.0.1",
    "swaggerDefinition": {
      "info": {
        "title": "Hobotti API",
        "description": "Basic API with Express",
        "version": "1.0.0"
      },
      "host": "localhost:3000",
      "basePath": "/api/",
      "tags": [{
        "name": "Users",
        "description": "Current user manipulation, authenticate JWT to use these methods"
      }, {
        "name": "Hobbies",
        "description": "Current user avatars manipulation, authenticate JWT to use these methods"
      }],
      "components": {
      "securitySchemes": {

        "BasicAuth": {
            "type": "http",
            "scheme": "basic"
        },

        "Access token": {
          "description": "The Access token given to you on a successul login or registration",
          "type": "apiKey",
          "name": "hobotti-access-token",
          "in": "header"
        }
      }
    },
      "security": [
        {
          "Access token": []
        }
      ]
    },
    "apis": [
      "./app.js",
      "./src/swgdef.js"
    ]
  }
  